{
  "doc_id": "0a41c71d7e66dc3c8fb663b9589a7a745b9bc10b169d6e668ca2c41b12c14949",
  "file_path": "C:\\Users\\blain\\Dropbox\\Master_Court_Files\\17_Medical\\Medical_Records_Dr._Tyler_Part_3.pdf",
  "file_name": "Medical_Records_Dr._Tyler_Part_3.pdf",
  "doc_type": "pdf",
  "date": null,
  "parties": [],
  "raw_text": "Patient:\n76861 - Adeline Kate McGregor\nDOB:\n05/24/20t2\nSSN:\nDate:\n031241202209:20\nProvider:\nTauro, Arnold J. MD\nEncounter: Pain in limbs, back, neck (not injury related)\nACTIVE FROELEMS\n.\nEczema\nCHIHF COMPLAINT\nThe Chief Complaint is: Left knee pain.\nHTS ORY OF PRESENT ILLNESS\nAdeline McGregor is a 9 year old female. Source of patient information was mother Source of\n. .\npatient information was patient Allergy list reviewed Medication list reviewed\n.\nPatient accompanied by mother\no No fever' and No chills o No headache \" No neck stiffness o No red eyes o No earache o\nNo nasal discharge o No sneezinB o , and No sore throat o No cough o No wheezing\nLeft knee pain for 1 week. She has been dancing and sprained her left knee. No fall. She dances 3 days a\nweek. No fever/joint swelling/other bone or joint pain\nNo cough,/runny nose/sore throaVabdominal pain/vomiting/diauhea/rash\nSleep fair, appetite fair\nOn Tylenol P:O PRN\nNo sick contacts\nCURRENT ME}ICI{TION\n.\nNone\nPAST MHNICAL/SURGICAL HISTORY\nReviewed on 3124122- Nl.\nSurgical:\n. Tonsillectomy\n. Adenoidectomy\nSOCIAL HIIiTCIRY\nThe racial background is caucasian.\nHousing And Economic Circumstances: Lives with married parents, unmarried parents, and lives in a\nprivate residence House. Housing has city water.\nLanguage / Communication: Native language English.\nReviewed on 3124122-Nl.\nALLEITGIES\n.\nNo Known Allergies\nFAMILY HTS'T'ORY\nNo family history of cancer\nPage 1\nPatient: 76861 - Adeline Kate McGregor\nDOB:\n0512412012\nSSN:\nDate:\n031241202209:20\nProvider: Tauro, Arnold J. MD\nEncounter: Pain in limbs, back, neck (not injury related)\nNo family history of heart disease\nNo family history of early deaths\nNo family history of kidney disease\nNo farnily history of allergies\nNl\nReviewed on 3124122--\nNo diagnosis of systemic hypertension\nNo diagnosis of asthma\nNo diagnosis of hepatitis\nNo diagnosis of diabetes mellitus\nNo diagnosis of epilepsy and recurrent seizures\nNo diagnosis of stroke syndrome\nNo diagnosis of depression\nNo diagnosis of HIV infection\nNo diagnosis of tuberculosis\nRSVIH,W OF SYS'I'HMS\nHead: No head symptoms.\nNeck: No neck symptoms.\nEyes: No eye symptoms.\nOtolaryngeal: No otolaryngeal symptoms.\nBreasts: No breast symptoms.\nCardiovascular: No cardiovascular symptoms.\nPulmonary: No pulmonary symptoms.\nGastrointestinal: No gastrointestinal symptoms.\nGenitourinary: No genitourinary symptoms.\nEndocrine: No endocrine symptoms.\nHematologic: No hematologic symptoms.\nMusculoskeletal: Musculoskeletal symptoms left knee pain.\nNeurological: No neurological symptoms.\nPsychological: No psychological symptoms.\nSkin: No skin symptoms.\nReview of systems reviewed\nReviewed on 3124122-Nl.\nPHYfiICAI, FINBTNGS\n.\nVitals taken03/241202209:77 am\nwt.77.8\nBP-Siuing L 98/62 mmHg 100 - 120/60 - 75\nBP Cuff Size Regular\nbpm\nPulse Rate-Sitting 58 60 - 95\nTemp-Temporal 97.8F 96-101\nin\nHeight 52.75 50 - 60\nWeight 77 lbs 8 oz 47 - 104\nBody Mass Index 19.6 kg/m2\nBMI Percentile 83 o/\"\nBody Surface Area t.L4m2\no/o\nOxygen Saturation 100 93 - 100\nPage 2\nPatient:\n76861 - Adeline Kate McGregor\nDOB:\n05/24/20t2\nSSN:\nDate:\n0312412022 09:20\nProvider:\nTauro, Arnold J. MD\nEncounter: Pain in limbs, back, neck (not injury related)\nGeneral Appearance:\no Alert. o In no acute distress. ' Not acutely ill.\nEyes:\nGeneraUbilateral:\no Eyes: normal.\nEars:\nGeneraUbilateral:\nExternal Auditory Canal: o No external auditory canal obstruction.\nRight Ear:\nTympanic Membrane: . Examined and normal.\nLeft Ear:\nTympanic Membrane: . Examined and normal.\nNose:\nGeneraUbilateral:\n. Nose: Hypertrophy of nasal turbinates.\nDischarge: o No nasal discharge seen.\nPharynx:\nOropharynx: o Not inflamed.\nLymph Nodes:\no No adenopathy.\nLungs:\n\" Clear to auscultation. o No wheezing was heard. o No rhonchi were heard. o No rales/crackles\nwere heard.\nCardiovascular:\nHeart Sounds: o Sl- normal. o 52 normal.\nMurmurs: o No murmurs were heard.\nAbdomen:\nPalpation:' Abdominal non-tender.\nLiver: o Normal to palpation.\nSpleen: o Normal to palpation.\nMusculoskeletal System:\nGeneral/bilateral: . Musculoskeletal system: mild swelling of the left knee medially. Soft tissue\ntenderness on medial aspect of the Ieft knee. No specific bony tenderness. Movements of the left\nknee painful. Antalgic gait.\nNeurological:\no Mental status was normal.\nMotor: o A motor exam demonstrated no dysfunction.\nCoordination / Cerebellum: o No coordination/cerebellum abnormalities were noted.\nBalance: \" Normal.\nGaitAnd Stance: . Abnormal antalgic gait.\nReflexes: o Deep tendon reflexes were normal.\nPsychiatric:\nAttitude: o Cooperative.\nSkin:\no No skin lesions.\nASSESSMHNT\n. Sprained left knee\nPage 3\nPatient: 76861 - Adeline Kate McGregor\nDOB: 05t24t2012\nSSN:\nDate: 031241202209:20\nProvider: Tauro,Arnold J. MD\nEncounter: Pain in limbs, back, neck (not injury related)\nPLAN\n. Return to the clinic if condition worsens or new symptoms arise\nXray left knee-- normal study-Al\nAdvil PO PRN\nKnee brace\nRestricted physical activity.\nArnold J. Thuro MD\nD.\nElectronically signed by: Arnold Thuro, M. Date: 03/2412022 t4:37\nPage 4\nV'Ai\nVLilcart Vulcan Imaging Associates\nlmaging\n2204 Lakeshore Dr., Sulte 400\nAs$rtcjates\nBirmingham, AL 35209\nP 205824 8000 F 205 824 Bl 1 1\nSeeing il through.\nPatlent Name: MCGREGOR, ADELINE Accession Nurnber: 001507108RUM\nPatlent lD: M0168401RUM Requested Daie: March 24, 2022 10:49\nGender: Female Report Status: Final\nDale of Birth: May24,2012 Requested Procedure: 1\nHome Phone: Procedure Descrlptlon: LEFT KNEE 4 VIEWS\nReferring Provlder: Tauro, Arnold Modallty: DX\nOrganlzation: RUM\nFindinos\nReportlng MD: Silvester, Nicholas\nDictatlon Time: March 24, 2O22 11:.13\nTranscrlptlonist: Not avallable\nTranscrlption Date:\nLEFT KNEE 4 VtEW(S)\nINDICATION / CLINICAL INFoRMATtON: PAIN tN L-KNEE\nCOMPARISON: None available,\nFINDINGS;\nBoNES / JoINT(s): No acute fracture or subluxation. No significant arthritis.\nSOFT TISSUES: No significant abnormality.\nADD ITIONAL FINDINGS: None-\nSigner Name: Nicholas C Silvester, DO\nSigned: 312412022 1 1:13 AM\nWorkstation Name: VIAPACS-W1 41 1 g\nRelevant Clinical lnformation\nPAIN IN L-KNEE\nPAIN IN L-KNEE\nV\nRadiology Associales of Blrmlngham - Report exported on Thu, Mar 24,2o221 1:2s:02 .osoo - page ,l of 1\nPatient:\n76861 - Adeline Kate McGregor\nDOB:\n05124120L2\nSSN:\nDate:\n0l/071202214:00\nProvider:\nEden, Ashley L. CPNP\nEncounter: Cough No Wheezing\nAC IVH PROtsLEMS\n.\nEczema\nC}IIHF CCIMPLAINT\nThe Chief Complaint is: Sore throat, cough, stuffy nose, exposure to Covid.\nHIS'TCIRY OF PITESENT ILLNESS\nAdeline McGregor is a 9 year old female.\n. Allergy list reviewed.\nPt here with mother. States that pt began having runny nose and cough 3 days ago. No fever.\nDrinking/eating well. Pt was exposed 4 days ago.\nCU}II{\"ENT MEDICAIION\n.\nNone\nPAS:T MENICAL/$URGICAI, HISTORY\nReviewed ll7l27 Ashley Eden CPNP.\nSurgical:\n. Tonsillectomy\n. Adenoidectomy\nSOCIAL HISTORY\nThe racial background is caucasian.\nHousing And Economic Circumstances: Lives with married parents, unmarried parents, and lives\nin a private residence House. Housing has city water.\nLanguage / Communication: Native language English.\nReviewed 1-/7/21Ashley Eden CPNP.\nALLER\"CIES\n.\nNo Known Allergies\nF'AMIIJ HISTOTTY\nNo family history of cancer\nNo family history of heart disease\nNo family history of early deaths\nNo family history of kidney disease\nNo family history of allergies\nPage 1\nPatient:\n76861 - Adeline Kate McGregor\nDOB:\n05124/2012\nSSN:\nDate:\n0110712022 L4:00\nProvider:\nEden, Ashley L. CPNP\nEncounter: Cough No Wheezing\nReviewed Ll7l21.Ashley Eden CPNP\nNo diagnosis of systemic hypertension\nNo diagnosis of asthma\nNo diagnosis of hepatitis\nNo diagnosis of diabetes mellitus\nNo diagnosis of epilepsy and recurrent seizures\nNo diagnosis of stroke syndrome\nNo diagnosis of depression\nNo diagnosis of HIV infection\nNo diagnosis of tuberculosis\nRHVIEW OF'SY$THMS\nOtolaryngeal: Otolaryngeal symptoms.\nPulmonary: Pulmonary symptoms.\nAll Systems Negative other than Previously Noted.\nAt least 10 Systems were reviewed.\nReview of systems reviewed and approved by performing provider on Reviewed 1-l7l21,Ashley\nEden CPNP.\nPHYSICAL FINDINGS\n.\nVitals taken 01/0712022 02:L9 pm\nRate-Sitting\nPulse 70 bpm\nTemp-Temporal\n97 F\nSaturation\nOxygen 1.00 %\nGeneral Appearance:\no Alert. o In no acute distress. o Not acutely ill.\nEyes:\nGeneraVbilateral:\no Eyes: normal.\nExternal: o Conjunctiva exhibited no abnormalities.\nEars:\nGeneraUbilateral:\nExternal Auditory Canal: o WalI normal. o Wall epithelium not reddened. o No external\nauditory canal obstruction.\nRight Ear:\nTympanic Membrane: . Examined and normal.\nLeft Ear:\nTympanic Membrane: . Examined and normal.\nNose:\nGeneral/bilateral:\nDischarge: . Cloudy nasal discharge.\nPharynx:\nPage 2\nPatient:\n76861 - Adeline Kate McGregor\nDOB:\n05/24/2012\nSSN:\nDate:\n0l/07120221.4:00\nProvider:\nEden, Ashley L. CPNP\nEncounter:\nCough No Wheezing\nOropharynx: o Tonsils were not swollen. o Tonsils were not erythematous. o Tonsils showed\nno exudate.\nLymph Nodes:\no Anterior cervical lymph nodes were not enlarged.\nLungs:\no Respiration rhythm and depth was normal. o Clear to auscultation. o No wheezing was\nheard. o No rhonchi were heard. o No rales/crackles were heard.\nCardiovascular:\nHeart Rate And Rhythm: o Normal.\nHeart Sounds: o 51 normal. o 52 normal.\nMurmurs: o No murmurs were heard.\nAbdomen:\nPalpation: o Abdominal non-tender.\nMusculoskeletal System:\nGeneral/bilateral: o Normal movement of all extremities.\nSkin:\no Color and pigmentation were normal.\nTrfi'1's\nNasal swab sent to Assurance Lab for COVID panel. -B. Simmons, RN\nA$SESSMENT\n. Upper respiratory infection\nTHERAPY\n. The options include close observation.\n.\nContinue current medication.\nPt to use OTC fever/pain product as needed per product instruction.\nC O UNSALIN G/ET' U C ATION\n. Parent education about medication use\nDISCI.JSSED\nQuarantine until covid results.\nPLAN\n. Return to the clinic if condition worsens or new symptoms arise\n. Follow-up visit as needed\nPage 3\nPatient: 76861 -Adeline Kate McGregor\nDOB: 0st24t2012\nSSN:\nDate: 0l/071202214:00\nProvider: Eden,Ashley L. CPNP\nEncounter: Cough No Wheezing\nAshley L. Eden CPNP\nElectronically signed by: Ashley Eden CRI\\P Date: 011071202214t38\nPage 4\nY\nru\nt\nru\nrc\nr\n1\n\\\ntrj\nI\nT",
  "source_metadata": {
    "method": "pdfplumber",
    "pages": 11
  },
  "modified_time": 1759007400.0
}