{
  "doc_id": "e0090f4669c0b72ff396c2410683c04771267095b15274e778738146f78aeacc",
  "file_path": "C:\\Users\\blain\\Dropbox\\Master_Court_Files\\01_Orders\\2025-09-02_ORDER_MOTION_TO_CONTINUE_DENIED_FILED_BY_BLAINE.pdf",
  "file_name": "2025-09-02_ORDER_MOTION_TO_CONTINUE_DENIED_FILED_BY_BLAINE.pdf",
  "doc_type": "pdf",
  "date": null,
  "parties": [],
  "raw_text": "AlaFile E-Notice\n70-DR-2023-900051.01\nJudge: KEVIN HALL\nTo: DAVIS DIANNE JAMES\ndianne@diannedavislaw.com\nNOTICE OF COURT ACTION\nIN THE CIRCUIT COURT OF TALLAPOOSA COUNTY, ALABAMA\nCHRISTOPHER BLAINE MCGREGOR V. BRITTANY MICHELLE GILLILAND\n70-DR-2023-900051.01\nA court action was entered in the above case on 9/2/2025 12:54:26 PM\nORDER\n[Filer: ]\nDisposition: DENIED\nJudge: KMH\nNotice Date: 9/2/2025 12:54:26 PM\nPATRICK CRADDOCK\nCIRCUIT COURT CLERK\nTALLAPOOSA COUNTY, ALABAMA\n395 LEE STREET\nALEXANDER CITY, AL, 35010\n256-234-4361\npatrick.craddock@alacourt.gov\nDOCUMENT 261\nELECTRONICALLY FILED\n9/2/2025 12:54 PM\n70-DR-2023-900051.01\nCIRCUIT COURT OF\nTALLAPOOSA COUNTY, ALABAMA\nPATRICK CRADDOCK, CLERK\nIN THE CIRCUIT COURT OF TALLAPOOSA COUNTY, ALABAMA\nALEX CITY DIVISION\nMCGREGOR CHRISTOPHER BLAINE, )\nPlaintiff, )\n)\nV. ) Case No.: DR-2023-900051.01\n)\nGILLILAND BRITTANY MICHELLE, )\nDefendant. )\nORDER\nMOTION TO CONTINUE filed by MCGREGOR CHRISTOPHER BLAINE is hereby\nDENIED.\nDONE this 2ndday of September, 2025.\n/s/ KEVIN HALL\nCIRCUIT JUDGE",
  "source_metadata": {
    "method": "pdfplumber",
    "pages": 2
  },
  "modified_time": 1758996312.0
}